gym_panda_shengyin/__init__.py
gym_panda_shengyin/envs/__init__.py
gym_panda_shengyin/envs/panda_env.py
gym_panda_shengyin-0.0.1.dist-info/LICENSE
gym_panda_shengyin-0.0.1.dist-info/METADATA
gym_panda_shengyin-0.0.1.dist-info/WHEEL
gym_panda_shengyin-0.0.1.dist-info/top_level.txt
gym_panda_shengyin-0.0.1.dist-info/RECORD
