Metadata-Version: 2.1
Name: gym-panda-shengyin
Version: 0.0.1
Summary: An OpenAI Gym Env for Panda
Home-page: UNKNOWN
Author: Shengyin Wang
Author-email: shengyin.wang@hotmail.com
License: UNKNOWN
Platform: UNKNOWN
Classifier: Programming Language :: Python :: 3
Classifier: License :: OSI Approved :: MIT License
Classifier: Operating System :: OS Independent
Requires-Python: >=3.6
Requires-Dist: gym
Requires-Dist: numpy
Requires-Dist: pybullet
